soraya_slog/__init__.py
soraya_slog-1.0.1.dist-info/LICENSE.txt
soraya_slog-1.0.1.dist-info/METADATA
soraya_slog-1.0.1.dist-info/WHEEL
soraya_slog-1.0.1.dist-info/top_level.txt
soraya_slog-1.0.1.dist-info/RECORD
