Metadata-Version: 2.1
Name: soraya-slog
Version: 1.0.1
Summary: A simple Python structured logging library that writes JSON-formatted output to stdout
Author-email: Rodrigo Laneth <contato@rlaneth.com>
Project-URL: Homepage, https://github.com/SliceOfFile/soraya_slog
Project-URL: Bug Tracker, https://github.com/SliceOfFile/soraya_slog/issues
Classifier: Programming Language :: Python :: 3
Classifier: License :: OSI Approved :: The Unlicense (Unlicense)
Classifier: Operating System :: OS Independent
Requires-Python: >=3.7
License-File: LICENSE.txt
